{"tracks":[["Pretty Little Life Form","Valley Maker","1IetAPA3SyGSUc8W0A5IOZ",{"danceability":0.519,"energy":0.381,"key":5,"loudness":-7.953,"mode":1,"speechiness":0.0283,"acousticness":0.609,"instrumentalness":0,"liveness":0.201,"valence":0.205,"tempo":99.53,"type":"audio_features","id":"1IetAPA3SyGSUc8W0A5IOZ","uri":"spotify:track:1IetAPA3SyGSUc8W0A5IOZ","track_href":"https://api.spotify.com/v1/tracks/1IetAPA3SyGSUc8W0A5IOZ","analysis_url":"https://api.spotify.com/v1/audio-analysis/1IetAPA3SyGSUc8W0A5IOZ","duration_ms":248853,"time_signature":4}],["Cleopatra","The Lumineers","2ToW7zhGCrVrLU4fiKj9U1",{"danceability":0.536,"energy":0.775,"key":8,"loudness":-6.765,"mode":1,"speechiness":0.0394,"acousticness":0.228,"instrumentalness":0.000143,"liveness":0.0947,"valence":0.485,"tempo":151.393,"type":"audio_features","id":"2ToW7zhGCrVrLU4fiKj9U1","uri":"spotify:track:2ToW7zhGCrVrLU4fiKj9U1","track_href":"https://api.spotify.com/v1/tracks/2ToW7zhGCrVrLU4fiKj9U1","analysis_url":"https://api.spotify.com/v1/audio-analysis/2ToW7zhGCrVrLU4fiKj9U1","duration_ms":201413,"time_signature":4}],["By My Side","Valley Maker","34qpxF5dEph6WqSCCANz8c",{"danceability":0.54,"energy":0.517,"key":6,"loudness":-8.193,"mode":0,"speechiness":0.0412,"acousticness":0.851,"instrumentalness":0.0000586,"liveness":0.106,"valence":0.357,"tempo":82.462,"type":"audio_features","id":"34qpxF5dEph6WqSCCANz8c","uri":"spotify:track:34qpxF5dEph6WqSCCANz8c","track_href":"https://api.spotify.com/v1/tracks/34qpxF5dEph6WqSCCANz8c","analysis_url":"https://api.spotify.com/v1/audio-analysis/34qpxF5dEph6WqSCCANz8c","duration_ms":194747,"time_signature":4}],["Lover's Cross","Jim Croce","3qHuiFe1gmlNjldCm1TfFM",{"danceability":0.706,"energy":0.362,"key":0,"loudness":-10.417,"mode":1,"speechiness":0.0329,"acousticness":0.804,"instrumentalness":0,"liveness":0.135,"valence":0.779,"tempo":120.532,"type":"audio_features","id":"3qHuiFe1gmlNjldCm1TfFM","uri":"spotify:track:3qHuiFe1gmlNjldCm1TfFM","track_href":"https://api.spotify.com/v1/tracks/3qHuiFe1gmlNjldCm1TfFM","analysis_url":"https://api.spotify.com/v1/audio-analysis/3qHuiFe1gmlNjldCm1TfFM","duration_ms":183440,"time_signature":4}],["Take Me to Church","Hozier","1CS7Sd1u5tWkstBhpssyjP",{"danceability":0.566,"energy":0.664,"key":4,"loudness":-5.303,"mode":0,"speechiness":0.0464,"acousticness":0.634,"instrumentalness":0,"liveness":0.116,"valence":0.437,"tempo":128.945,"type":"audio_features","id":"1CS7Sd1u5tWkstBhpssyjP","uri":"spotify:track:1CS7Sd1u5tWkstBhpssyjP","track_href":"https://api.spotify.com/v1/tracks/1CS7Sd1u5tWkstBhpssyjP","analysis_url":"https://api.spotify.com/v1/audio-analysis/1CS7Sd1u5tWkstBhpssyjP","duration_ms":241693,"time_signature":4}]]}